hydrointerp/__init__.py
hydrointerp/core.py
hydrointerp/interp2d.py
hydrointerp/util.py
hydrointerp/datasets/__init__.py
hydrointerp/datasets/ecan_data_2015-06-18.csv
hydrointerp/datasets/nasa_gpm_2015-06-18.nc
hydrointerp/io/__init__.py
hydrointerp/io/metservice.py
hydrointerp/io/nasa.py
hydrointerp/io/raster.py
hydrointerp/tests/__init__.py
hydrointerp/tests/nasa_gpm_assessments.py
hydrointerp/tests/station_correction.py
hydrointerp/tests/test_interp2d.py
hydrointerp/tests/utest_adj_grid_from_points.py
hydrointerp-1.2.13.dist-info/LICENSE.txt
hydrointerp-1.2.13.dist-info/METADATA
hydrointerp-1.2.13.dist-info/WHEEL
hydrointerp-1.2.13.dist-info/top_level.txt
hydrointerp-1.2.13.dist-info/RECORD
