Metadata-Version: 2.1
Name: hydrointerp
Version: 1.2.13
Summary: Functions for interpolating hydrologic features
Home-page: https://github.com/mullenkamp/hydrointerp
Author: Mike Kittridge
Author-email: mullenkamp1@gmail.com
License: Apache
Keywords: interpolation
Classifier: Development Status :: 3 - Alpha
Classifier: Intended Audience :: Developers
Classifier: Topic :: Software Development :: Build Tools
Classifier: License :: OSI Approved :: Apache Software License
Classifier: Programming Language :: Python :: 2
Classifier: Programming Language :: Python :: 2.7
Classifier: Programming Language :: Python :: 3
Classifier: Programming Language :: Python :: 3.4
Classifier: Programming Language :: Python :: 3.5
Classifier: Programming Language :: Python :: 3.6
License-File: LICENSE.txt
Requires-Dist: pandas
Requires-Dist: scipy
Requires-Dist: xarray
Requires-Dist: pyproj (>=2.1)
Requires-Dist: netcdf4
Provides-Extra: fiona
Requires-Dist: fiona ; extra == 'fiona'
Provides-Extra: rasterio
Requires-Dist: rasterio ; extra == 'rasterio'
